{
    "last_update": "30.01.2026 19:39",
    "highlights": {
        "analyses": 92,
        "won": 68,
        "lose": 24,
        "success_rate": "%73.91"
    },
    "top_matches": [
        {
            "league": "EGY2",
            "home": "Aswan Fc",
            "away": "Telecom Egypt",
            "iy_score": "0 - 1",
            "ms_score": "0 - 1",
            "prediction": "Match Result 2",
            "odd": "2.71",
            "date": "30.01.2026 12:30"
        },
        {
            "league": "UEL",
            "home": "Nottingham Forest",
            "away": "Ferencvaros",
            "iy_score": "2 - 0",
            "ms_score": "4 - 0",
            "prediction": "1st Half Over 1.5",
            "odd": "2.55",
            "date": "29.01.2026 20:00"
        },
        {
            "league": "UEL",
            "home": "Ludogorets",
            "away": "Nice",
            "iy_score": "1 - 0",
            "ms_score": "1 - 0",
            "prediction": "HT/FT 1/1",
            "odd": "2.23",
            "date": "29.01.2026 20:00"
        },
        {
            "league": "UGA",
            "home": "Updf",
            "away": "Bul",
            "iy_score": "0 - 1",
            "ms_score": "0 - 1",
            "prediction": "Match Result 2",
            "odd": "2.04",
            "date": "30.01.2026 13:00"
        },
        {
            "league": "UEL",
            "home": "Ludogorets",
            "away": "Nice",
            "iy_score": "1 - 0",
            "ms_score": "1 - 0",
            "prediction": "1st Half Result 1",
            "odd": "2.01",
            "date": "29.01.2026 20:00"
        }
    ]
}